CHANGES.rst
CONTRIBUTING.rst
LICENSE
MANIFEST.in
README.rst
setup.cfg
setup.py
asana_kazoo.egg-info/PKG-INFO
asana_kazoo.egg-info/SOURCES.txt
asana_kazoo.egg-info/dependency_links.txt
asana_kazoo.egg-info/not-zip-safe
asana_kazoo.egg-info/requires.txt
asana_kazoo.egg-info/top_level.txt
kazoo/__init__.py
kazoo/client.py
kazoo/exceptions.py
kazoo/hosts.py
kazoo/interfaces.py
kazoo/loggingsupport.py
kazoo/python2atexit.py
kazoo/python2atexit.py~
kazoo/retry.py
kazoo/security.py
kazoo/handlers/__init__.py
kazoo/handlers/gevent.py
kazoo/handlers/gevent.py~
kazoo/handlers/python2atexit.py~
kazoo/handlers/threading.py
kazoo/handlers/threading.py~
kazoo/handlers/utils.py
kazoo/protocol/__init__.py
kazoo/protocol/connection.py
kazoo/protocol/paths.py
kazoo/protocol/serialization.py
kazoo/protocol/states.py
kazoo/recipe/__init__.py
kazoo/recipe/barrier.py
kazoo/recipe/counter.py
kazoo/recipe/election.py
kazoo/recipe/lock.py
kazoo/recipe/partitioner.py
kazoo/recipe/party.py
kazoo/recipe/queue.py
kazoo/recipe/watchers.py
kazoo/testing/__init__.py
kazoo/testing/common.py
kazoo/testing/harness.py
kazoo/tests/__init__.py
kazoo/tests/test_barrier.py
kazoo/tests/test_build.py
kazoo/tests/test_client.py
kazoo/tests/test_connection.py
kazoo/tests/test_counter.py
kazoo/tests/test_election.py
kazoo/tests/test_exceptions.py
kazoo/tests/test_gevent_handler.py
kazoo/tests/test_lock.py
kazoo/tests/test_partitioner.py
kazoo/tests/test_party.py
kazoo/tests/test_paths.py
kazoo/tests/test_queue.py
kazoo/tests/test_retry.py
kazoo/tests/test_security.py
kazoo/tests/test_threading_handler.py
kazoo/tests/test_watchers.py
kazoo/tests/util.py